aws_layers/__init__.py
aws_layers/aws_layers.py
aws_layers/layer_utils.py
python_layer-1.2.2.data/scripts/layer
python_layer-1.2.2.dist-info/LICENSE
python_layer-1.2.2.dist-info/METADATA
python_layer-1.2.2.dist-info/WHEEL
python_layer-1.2.2.dist-info/top_level.txt
python_layer-1.2.2.dist-info/RECORD
