Metadata-Version: 2.1
Name: python-layer
Version: 1.2.2
Summary: Manage aws layers
Home-page: UNKNOWN
Author: Charalampos Mageiridis
Author-email: cmageiridis@protonmail.com
License: MIT
Platform: UNKNOWN
Classifier: License :: OSI Approved :: MIT License
Classifier: Programming Language :: Python :: 3
Classifier: Programming Language :: Python :: 3.7
Requires-Dist: boto3 (==1.12.36)
Requires-Dist: wget (==3.2)
Requires-Dist: Click (==7.1.1)
